lakewatch_api/api/workspace_v1_api.py
lakewatch_api/api/__init__.py
lakewatch_api/api/dbui_v1_api.py
lakewatch_api/api/content_v1_api.py
lakewatch_api/api/core_v1_api.py
lakewatch_api/__init__.py
lakewatch_api/configuration.py
lakewatch_api/api_response.py
lakewatch_api/models/dbui_v1_create_notebook_response.py
lakewatch_api/models/core_v1_query_spec.py
lakewatch_api/models/core_v1_case_event_list.py
lakewatch_api/models/workspace_v1_authenticate_response.py
lakewatch_api/models/core_v1_case_list.py
lakewatch_api/models/core_v1_rendered_rule_tables.py
lakewatch_api/models/content_v1_datasource_preset_bronze.py
lakewatch_api/models/content_v1_datasource_preset_gold_inner.py
lakewatch_api/models/core_v1_data_source_spec_silver_transform_preset_overrides_modify_tables_inner.py
lakewatch_api/models/core_v1_workspace_access_configuration.py
lakewatch_api/models/resource_exhausted_error.py
lakewatch_api/models/dbui_v1_autoloader_preview_status.py
lakewatch_api/models/dbui_v1_operational_alert_list.py
lakewatch_api/models/core_v1_migration_status.py
lakewatch_api/models/core_v1_rule_observable.py
lakewatch_api/models/core_v1_migration_list.py
lakewatch_api/models/workspace_v1_export_config_service_now_config_password.py
lakewatch_api/models/dbui_v1_transform_response_stages_inner.py
lakewatch_api/models/core_v1_preview_stage.py
lakewatch_api/models/content_v1_datasource_preset_autoloader_cloud_files.py
lakewatch_api/models/workspace_v1_workspace_config_spec_observables.py
lakewatch_api/models/workspace_v1_export_config_slack_config_token.py
lakewatch_api/models/content_v1_datasource_preset_version_list.py
lakewatch_api/models/workspace_v1_workspace_config_spec_managed_retention_inner_overrides_inner.py
lakewatch_api/models/core_v1_update_case_request.py
lakewatch_api/models/core_v1_query_spec_date_range.py
lakewatch_api/models/core_v1_post_rule_metrics_request_exec_results_inner.py
lakewatch_api/models/dbui_v1_transform_request_ingestion_input.py
lakewatch_api-0.1.1.dist-info/WHEEL
lakewatch_api-0.1.1.dist-info/METADATA
lakewatch_api-0.1.1.dist-info/RECORD
