Metadata-Version: 2.1
Name: lakewatch_api
Requires-Dist: python-dateutil>=2.8.2
Requires-Dist: pydantic>=2
Requires-Dist: typing-extensions>=4.7.1
Requires-Dist: urllib3>=2.1.0,<3.0.0
Version: 0.1.1
